carbem.libs/libcrypto-c19c2cf8.so.3
carbem.libs/libssl-63597a81.so.3
carbem/__init__.py
carbem/carbem.cpython-313-x86_64-linux-gnu.so
carbem_python-0.4.0.dist-info/METADATA
carbem_python-0.4.0.dist-info/WHEEL
carbem_python-0.4.0.dist-info/RECORD
