Metadata-Version: 2.4
Name: carbem-python
Version: 0.4.0
Classifier: Development Status :: 3 - Alpha
Classifier: Intended Audience :: Developers
Classifier: Programming Language :: Rust
Classifier: Programming Language :: Python :: 3
Classifier: Programming Language :: Python :: Implementation :: CPython
Classifier: Topic :: Software Development :: Libraries :: Python Modules
Requires-Dist: maturin[patchelf]>=1.9.6
Summary: Python wrapper for the carbem library - retrieve carbon emission data from cloud providers
Keywords: carbon,emissions,cloud,sustainability
Author-email: Jonathan Perron <jonathan@perron.bzh>
License-Expression: Apache-2.0
Requires-Python: >=3.11
Project-URL: Source, https://github.com/jonperron/carbem
